repomate_junit4/__init__.py
repomate_junit4/__version.py
repomate_junit4/_java.py
repomate_junit4/_junit4_runner.py
repomate_junit4/junit4.py
repomate_junit4-0.5.0.dist-info/LICENSE
repomate_junit4-0.5.0.dist-info/METADATA
repomate_junit4-0.5.0.dist-info/WHEEL
repomate_junit4-0.5.0.dist-info/top_level.txt
repomate_junit4-0.5.0.dist-info/RECORD
