Metadata-Version: 2.1
Name: repomate-junit4
Version: 0.5.0
Summary: JUnit-4.12 plugin for repomate
Home-page: https://github.com/slarse/repomate-junit4
Author: Simon Larsén
Author-email: slarse@kth.se
License: MIT
Download-URL: https://github.com/slarse/repomate-junit4/archive/v0.5.0.tar.gz
Platform: UNKNOWN
Classifier: Development Status :: 4 - Beta
Classifier: Intended Audience :: Education
Classifier: Programming Language :: Python :: 3.5
Classifier: Programming Language :: Python :: 3.6
Classifier: Programming Language :: Python :: 3.7
Classifier: Programming Language :: Python :: Implementation :: CPython
Classifier: License :: OSI Approved :: MIT License
Classifier: Operating System :: POSIX
Requires-Dist: repomate-plug (>=0.4.1)
Requires-Dist: daiquiri
Requires-Dist: colored
Provides-Extra: test
Requires-Dist: appdirs ; extra == 'test'
Requires-Dist: daiquiri ; extra == 'test'
Requires-Dist: pytest (>=4.0.0) ; extra == 'test'
Requires-Dist: pytest-cov (>=2.5.1) ; extra == 'test'
Requires-Dist: pytest-mock ; extra == 'test'
Requires-Dist: codecov ; extra == 'test'
